README.rst
setup.py
simpress/__init__.py
simpress/builder.py
simpress/commands.py
simpress/logger.py
simpress/page.py
simpress/web.py
simpress.egg-info/PKG-INFO
simpress.egg-info/SOURCES.txt
simpress.egg-info/dependency_links.txt
simpress.egg-info/entry_points.txt
simpress.egg-info/top_level.txt