Metadata-Version: 1.1
Name: simpress
Version: 0.1.1
Summary: Simple document system by GitHub flavored Markdown.
Home-page: http://github.com/nekoya/simpress
Author: Ryo Miyake
Author-email: ryo.studiom@gmail.com
License: MIT
Platform: UNKNOWN
Classifier: Development Status :: 2 - Pre-Alpha
Classifier: Environment :: Web Environment
Classifier: Intended Audience :: Developers
Classifier: License :: OSI Approved :: MIT License
Classifier: Operating System :: OS Independent
Classifier: Programming Language :: Python
Classifier: Topic :: Documentation
